particle_field/__init__.py
particle_field/ai_bridge.py
particle_field/controller.py
particle_field/field.py
particle_field/morph_visual.py
particle_field/shapes.py
particle_field-0.2.0.dist-info/METADATA
particle_field-0.2.0.dist-info/WHEEL
particle_field-0.2.0.dist-info/top_level.txt
particle_field-0.2.0.dist-info/RECORD
