Metadata-Version: 2.4
Name: particle-field
Version: 0.2.0
Summary: Pure-Python, GPU-accelerated particle morphing library
Author-email: Josh James <josh@rocketnow.com>
Requires-Python: >=3.8
Requires-Dist: numpy>=1.19
Requires-Dist: opensimplex>=0.1.2
Requires-Dist: vispy>=0.9
